mystmd_py/__init__.py
mystmd_py/main.py
mystmd_py/myst.cjs
mystmd_py/nodeenv.py
mystmd-1.8.0.dist-info/METADATA
mystmd-1.8.0.dist-info/WHEEL
mystmd-1.8.0.dist-info/entry_points.txt
mystmd-1.8.0.dist-info/licenses/LICENSE
mystmd-1.8.0.dist-info/RECORD
