Metadata-Version: 2.4
Name: mystmd
Version: 1.8.0
Summary: Command line tools for MyST Markdown
Project-URL: Homepage, https://github.com/jupyter-book/mystmd
Project-URL: Bug Tracker, https://github.com/jupyter-book/mystmd/issues
Project-URL: Repository, https://github.com/jupyter-book/mystmd.git
Author-email: Rowan Cockett <rowan@curvenote.com>
License-Expression: MIT
License-File: LICENSE
Keywords: latex,markdown,pdf-generation,science-research,scientific-visualization,writing-software
Classifier: Intended Audience :: Science/Research
Classifier: License :: OSI Approved :: MIT License
Classifier: Operating System :: OS Independent
Classifier: Programming Language :: JavaScript
Classifier: Programming Language :: Python :: 3
Classifier: Programming Language :: Python :: 3.8
Classifier: Programming Language :: Python :: 3.9
Classifier: Programming Language :: Python :: 3.10
Classifier: Programming Language :: Python :: 3.11
Classifier: Programming Language :: Python :: 3.12
Classifier: Topic :: Scientific/Engineering
Requires-Python: >=3.8
Requires-Dist: platformdirs~=4.2.2
Requires-Dist: nodeenv~=1.9.1
Provides-Extra: execute
Requires-Dist: ipykernel; extra == 'execute'
Requires-Dist: jupyter-server; extra == 'execute'
